fluidfoam/__init__.py
fluidfoam/_version.py
fluidfoam/meshdesign.py
fluidfoam/meshvisu.py
fluidfoam/openfoamsimu.py
fluidfoam/processing1d.py
fluidfoam/readof.py
fluidfoam/readpostpro.py
fluidfoam/test_create1dprofil.py
fluidfoam/test_create1dprofilDFSEM.py
fluidfoam/test_meshdesign.py
fluidfoam/test_meshvisu.py
fluidfoam/test_openfoamsimu.py
fluidfoam/test_read.py
fluidfoam/test_readpostpro.py
fluidfoam-0.2.9.dist-info/AUTHORS.txt
fluidfoam-0.2.9.dist-info/LICENSE
fluidfoam-0.2.9.dist-info/METADATA
fluidfoam-0.2.9.dist-info/WHEEL
fluidfoam-0.2.9.dist-info/top_level.txt
fluidfoam-0.2.9.dist-info/RECORD
